[
    {
        "body": [
            "- action: aws:runPowerShellScript",
            "\tname: exampleRunPowerShellScript",
            "\tinputs:",
            "\t\ttimeoutSeconds: '60'",
            "\t\trunCommand:",
            "\t\t- \"{{ commands }}\""
        ],
        "name": "$Plugin Snippet aws:runPowerShellScript",
        "description": "Insert Snippet for aws:runPowerShellScript.\n\nRun PowerShell scripts or specify the path to a script to run. This plugin runs on Microsoft Windows Server and Linux operating systems."
    },
    {
        "body": [
            "- action: aws:runDocument",
            "\tname: exampleRunDocument",
            "\tinputs:",
            "\t\tdocumentType: \"{{ documentType }}\""
        ],
        "name": "$Plugin Snippet aws:runDocument",
        "description": "Insert Snippet for aws:runDocument.\n\n(Schema version 2.0 or later) Runs SSM documents stored in Systems Manager or on a local share. You can use this plugin with the aws:downloadContent plugin to download an SSM document from a remote location to a local share, and then run it. This plugin is supported on Linux and Windows Server operating systems."
    },
    {
        "body": [
            "- action: aws:refreshAssociation",
            "\tname: exampleRefreshAssociation",
            "\tinputs:",
            "\t\tassociationIds:",
            "\t\t- \"{{ associationIds }}\""
        ],
        "name": "$Plugin Snippet aws:refreshAssociation",
        "description": "Insert Snippet for aws:refreshAssociation.\n\n(Schema version 2.0 or later) Refresh (force apply) an association on demand. This action will change the system state based on what is defined in the selected association or all associations bound to the targets. This plugin runs on Linux and Microsoft Windows Server operating systems."
    },
    {
        "body": [
            "- action: aws:domainJoin",
            "\tname: exampleDomainJoin",
            "\tinputs:",
            "\t\tdirectoryId: \"{{ directoryId }}\"",
            "\t\tdirectoryName: \"{{ directoryName }}\""
        ],
        "name": "$Plugin Snippet aws:domainJoin",
        "description": "Insert Snippet for aws:domainJoin.\n\nJoin an EC2 instance to a domain. This plugin only runs on Windows Server operating systems."
    },
    {
        "body": [
            "- action: aws:updateAgent",
            "\tname: exampleUpdateAgent",
            "\tinputs:",
            "\t\tagentName: Ec2Config",
            "\t\tsource: https://s3.{Region}.amazonaws.com/aws-ssm-{Region}/manifest.json"
        ],
        "name": "$Plugin Snippet aws:updateAgent",
        "description": "Insert Snippet for aws:updateAgent.\n\nUpdate the EC2Config service to the latest version or specify an older version. This plugin only runs on Microsoft Windows Server operating systems."
    },
    {
        "body": [
            "- action: aws:updateSsmAgent",
            "\tname: exampleUpdateSSMAgent",
            "\tinputs:",
            "\t\tagentName: amazon-ssm-agent",
            "\t\tsource: https://s3.{Region}.amazonaws.com/amazon-ssm-{Region}/ssm-agent-manifest.json",
            "\t\tallowDowngrade: \"{{ allowDowngrade }}\""
        ],
        "name": "$Plugin Snippet aws:updateSsmAgent",
        "description": "Insert Snippet for aws:updateSsmAgent.\n\nUpdate the SSM Agent to the latest version or specify an older version. This plugin runs on Linux and Windows Server operating systems. "
    },
    {
        "body": [
            "- action: aws:runShellScript",
            "\tname: exampleRunShellScript",
            "\tinputs:",
            "\t\ttimeoutSeconds: '60'",
            "\t\trunCommand:",
            "\t\t- \"{{ commands }}\""
        ],
        "name": "$Plugin Snippet aws:runShellScript",
        "description": "Insert Snippet for aws:runShellScript.\n\nRun Linux shell scripts or specify the path to a script to run. This plugin only runs on Linux operating systems."
    },
    {
        "body": [
            "- action: aws:configurePackage",
            "\tname: exampleConfigurePackage",
            "\tinputs:",
            "\t\tname: \"{{ name }}\"",
            "\t\taction: \"{{ action }}\""
        ],
        "name": "$Plugin Snippet aws:configurePackage",
        "description": "Insert Snippet for aws:configurePackage.\n\n(Schema version 2.0 or later) Install or uninstall a Distributor package. You can install the latest version, default version, or a version of the package you specify. Packages provided by AWS are also supported. This plugin runs on Windows Server and Linux operating systems, but not all the available packages are supported on Linux operating systems.\n\nAvailable AWS packages for Windows Server include the following: AWSPVDriver, AWSNVMe, AwsEnaNetworkDriver, AwsVssComponents, AmazonCloudWatchAgent, and AWSSupport-EC2Rescue.\n\nAvailable AWS packages for Linux operating systems include the following: AmazonCloudWatchAgent and AWSSupport-EC2Rescue."
    },
    {
        "body": [
            "- action: aws:applications",
            "\tname: exampleApplications",
            "\tinputs:",
            "\t\taction: Install",
            "\t\tsource: \"{{ source }}\""
        ],
        "name": "$Plugin Snippet aws:applications",
        "description": "Insert Snippet for aws:applications.\n\nInstall, repair, or uninstall applications on an EC2 instance. This plugin only runs on Windows Server operating systems."
    },
    {
        "body": [
            "- action: aws:downloadContent",
            "\tname: exampleDownloadContent",
            "\tinputs:",
            "\t\tsourceType: Github",
            "\t\tsourceInfo:",
            "\t\t\towner: TestUser",
            "\t\t\trepository: GithubTest",
            "\t\t\tpath: scripts/python/test-script",
            "\t\t\tgetOptions: branch:master",
            "\t\t\ttokenInfo: \"{{ssm-secure:secure-string-token}}\""
        ],
        "name": "$Plugin Snippet aws:downloadContent",
        "description": "Insert Snippet for aws:downloadContent.\n\n(Schema version 2.0 or later) Download SSM documents and scripts from remote locations. This plugin is supported on Linux and Windows Server operating systems."
    },
    {
        "body": [
            "- action: aws:softwareInventory",
            "\tname: exampleSoftwareInventoryItems",
            "\tinputs:",
            "\t\tapplications: \"{{ applications }}\"",
            "\t\tawsComponents: \"{{ awsComponents }}\"",
            "\t\tnetworkConfig: \"{{ networkConfig }}\"",
            "\t\tfiles: \"{{ files }}\"",
            "\t\tservices: \"{{ services }}\"",
            "\t\twindowsRoles: \"{{ windowsRoles }}\"",
            "\t\twindowsRegistry: \"{{ windowsRegistry}}\"",
            "\t\twindowsUpdates: \"{{ windowsUpdates }}\"",
            "\t\tinstanceDetailedInformation: \"{{ instanceDetailedInformation }}\"",
            "\t\tcustomInventory: \"{{ customInventory }}\""
        ],
        "name": "$Plugin Snippet aws:softwareInventory",
        "description": "Insert Snippet for aws:softwareInventory.\n\n(Schema version 2.0 or later) Gather metadata about applications, files, and configurations on your managed instances. This plugin runs on Linux and Microsoft Windows Server operating systems."
    },
    {
        "body": [
            "- action: aws:configureDocker",
            "\tname: exampleConfigureDocker",
            "\tinputs:",
            "\t\taction: \"{{ action }}\""
        ],
        "name": "$Plugin Snippet aws:configureDocker",
        "description": "Insert Snippet for aws:configureDocker.\n\n(Schema version 2.0 or later) Configure an instance to work with containers and Docker. This plugin is supported on Linux and Windows Server operating systems."
    },
    {
        "body": [
            "- action: aws:runDockerAction",
            "\tname: exampleRunDockerAction",
            "\tinputs:",
            "\t\taction: \"{{ action }}\"",
            "\t\tcontainer: \"{{ container }}\"",
            "\t\timage: \"{{ image }}\"",
            "\t\tmemory: \"{{ memory }}\"",
            "\t\tcpuShares: \"{{ cpuShares }}\"",
            "\t\tvolume: \"{{ volume }}\"",
            "\t\tcmd: \"{{ cmd }}\"",
            "\t\tenv: \"{{ env }}\"",
            "\t\tuser: \"{{ user }}\"",
            "\t\tpublish: \"{{ publish }}\""
        ],
        "name": "$Plugin Snippet aws:runDockerAction",
        "description": "Insert Snippet for aws:runDockerAction.\n\n(Schema version 2.0 or later) Run Docker actions on containers. This plugin runs on Linux and Microsoft Windows Server operating systems."
    },
    {
        "body": ["- action: aws:psModule", "\tname: examplePsModule", "\tinputs:", "\t\tsource: \"{{ source }}\""],
        "name": "$Plugin Snippet aws:psModule",
        "description": "Insert Snippet for aws:psModule.\n\nInstall PowerShell modules on an EC2 instance. This plugin only runs on Windows Server operating systems."
    }
]
